mediawiki_dump/__init__.py
mediawiki_dump/dumps.py
mediawiki_dump/entry.py
mediawiki_dump/reader.py
mediawiki_dump/tokenizer.py
mediawiki_dump/utils.py
test/__init__.py
test/test_dumps.py
test/test_entry.py
test/test_local_file_dump.py
test/test_reader.py
test/test_tokenizer.py
test/test_utils.py
mediawiki_dump-1.4.0.dist-info/LICENSE
mediawiki_dump-1.4.0.dist-info/METADATA
mediawiki_dump-1.4.0.dist-info/WHEEL
mediawiki_dump-1.4.0.dist-info/top_level.txt
mediawiki_dump-1.4.0.dist-info/RECORD
