Metadata-Version: 2.2
Name: mediawiki_dump
Version: 1.4.0
Summary: Python package for working with MediaWiki XML content dumps
Home-page: https://github.com/macbre/mediawiki-dump
Author: Maciej Brencz
Author-email: maciej.brencz@gmail.com
License: MIT
Keywords: dump fandom mediawiki wikipedia wikia xml
Classifier: Development Status :: 5 - Production/Stable
Classifier: Intended Audience :: Science/Research
Classifier: Topic :: Text Processing :: Markup :: XML
Classifier: License :: OSI Approved :: MIT License
Requires-Python: >=3.9
License-File: LICENSE
Requires-Dist: libarchive-c==5.1
Requires-Dist: requests>=2.26.0
Requires-Dist: mwclient>=0.10.1
Provides-Extra: dev
Requires-Dist: black==25.1.0; extra == "dev"
Requires-Dist: pylint==3.3.4; extra == "dev"
Requires-Dist: pytest==8.3.4; extra == "dev"
Requires-Dist: pytest-cov==6.0.0; extra == "dev"
Requires-Dist: responses==0.25.6; extra == "dev"
Dynamic: author
Dynamic: author-email
Dynamic: classifier
Dynamic: description
Dynamic: description-content-type
Dynamic: home-page
Dynamic: keywords
Dynamic: license
Dynamic: provides-extra
Dynamic: requires-dist
Dynamic: requires-python
Dynamic: summary
